tortugo/__init__.py
tortugo-0.0.1.dist-info/LICENSE
tortugo-0.0.1.dist-info/METADATA
tortugo-0.0.1.dist-info/WHEEL
tortugo-0.0.1.dist-info/top_level.txt
tortugo-0.0.1.dist-info/RECORD
