Metadata-Version: 2.1
Name: tortugo
Version: 0.0.1
Summary: Latam translation of the turtle module
Home-page: https://github.com/VladimirCharkot/tortugo
Author: Vladimir Charkot
Author-email: vlad.chk@gmail.com
License: UNKNOWN
Platform: UNKNOWN
Classifier: Programming Language :: Python :: 3
Classifier: License :: OSI Approved :: MIT License
Classifier: Operating System :: OS Independent
Requires-Python: >=3.6
